pylib_fftw3/__init__.py
pylib_fftw3/placeholder.cp36-win32.pyd
pylib_fftw3/include/fftw3.f
pylib_fftw3/include/fftw3.f03
pylib_fftw3/include/fftw3.h
pylib_fftw3/include/fftw3l.f03
pylib_fftw3/include/fftw3q.f03
pylib_fftw3/lib/fftw3.lib
pylib_fftw3/lib/cmake/fftw3/FFTW3Config.cmake
pylib_fftw3/lib/cmake/fftw3/FFTW3ConfigVersion.cmake
pylib_fftw3/lib/cmake/fftw3/FFTW3LibraryDepends-debug.cmake
pylib_fftw3/lib/cmake/fftw3/FFTW3LibraryDepends.cmake
pylib_fftw3/lib/pkgconfig/fftw3.pc
pylib_fftw3-0.0.2.dist-info/METADATA
pylib_fftw3-0.0.2.dist-info/WHEEL
pylib_fftw3-0.0.2.dist-info/top_level.txt
pylib_fftw3-0.0.2.dist-info/RECORD
