Metadata-Version: 2.1
Name: pylib_fftw3
Version: 0.0.2
Summary: Python packaging of FFTW3 3.3.10
Author: chenkui164
